{
  "schema_version": "v1",
  "name_for_model": "computer_use",
  "name_for_human": "Computer Control",
  "description_for_model": "Plugin to control the computer using keyboard and mouse inputs, and to take screenshots.",
  "description_for_human": "Allows the AI to control the computer's mouse and keyboard.",
  "auth": {
    "type": "none"
  },
  "api": {
    "type": "openapi",
    "url": "http://localhost:0/openapi.yaml",
    "is_user_authenticated": false
  },
  "logo_url": "http://localhost:0/logo.png",
  "contact_email": "support@example.com",
  "legal_info_url": "http://www.example.com/legal"
}
